financial_fraud
